{
  "status": 200,
  "url": "https://api.github.com/repos/github/GitHub-EcoSystem/issues/475/events?per_page=100",
  "headers": {
    "access-control-allow-origin": "*",
    "access-control-expose-headers": "ETag, Link, Location, Retry-After, X-GitHub-OTP, X-RateLimit-Limit, X-RateLimit-Remaining, X-RateLimit-Used, X-RateLimit-Reset, X-OAuth-Scopes, X-Accepted-OAuth-Scopes, X-Poll-Interval, X-GitHub-Media-Type, Deprecation, Sunset",
    "cache-control": "private, max-age=60, s-maxage=60",
    "connection": "close",
    "content-encoding": "gzip",
    "content-security-policy": "default-src 'none'",
    "content-type": "application/json; charset=utf-8",
    "date": "Wed, 30 Sep 2020 10:58:59 GMT",
    "etag": "W/\"7010e94e9bbd9e81a43f2d4ab67715fa0a5dede1db36e825d7c98dce96729862\"",
    "referrer-policy": "origin-when-cross-origin, strict-origin-when-cross-origin",
    "server": "GitHub.com",
    "status": "200 OK",
    "strict-transport-security": "max-age=31536000; includeSubdomains; preload",
    "transfer-encoding": "chunked",
    "vary": "Accept, Authorization, Cookie, X-GitHub-OTP, Accept-Encoding, Accept, X-Requested-With",
    "x-accepted-oauth-scopes": "repo",
    "x-content-type-options": "nosniff",
    "x-frame-options": "deny",
    "x-github-media-type": "github.squirrel-girl-preview; format=json, github.inertia-preview; format=json, github.starfox-preview; format=json, github.mockingbird-preview; param=sailor-v-preview; format=json, github.squirrel-girl-preview; format=json, github.inertia-preview; format=json, github.starfox-preview; format=json, github.mockingbird-preview; param=sailor-v-preview; format=json",
    "x-github-request-id": "07BD:0728:92335E:14A0AC9:5F7464F3",
    "x-oauth-scopes": "admin:enterprise, admin:gpg_key, admin:org, admin:org_hook, admin:public_key, admin:repo_hook, gist, repo, user, workflow, write:discussion, write:packages",
    "x-ratelimit-limit": "5000",
    "x-ratelimit-remaining": "3821",
    "x-ratelimit-reset": "1601465977",
    "x-ratelimit-used": "1179",
    "x-xss-protection": "1; mode=block"
  },
  "data": [
    {
      "id": 3781407980,
      "node_id": "MDEyOkxhYmVsZWRFdmVudDM3ODE0MDc5ODA=",
      "url": "https://api.github.com/repos/github/GitHub-EcoSystem/issues/events/3781407980",
      "actor": {
        "login": "azooinmyluggage",
        "id": 6857119,
        "node_id": "MDQ6VXNlcjY4NTcxMTk=",
        "avatar_url": "https://avatars2.githubusercontent.com/u/6857119?v=4",
        "gravatar_id": "",
        "url": "https://api.github.com/users/azooinmyluggage",
        "html_url": "https://github.com/azooinmyluggage",
        "followers_url": "https://api.github.com/users/azooinmyluggage/followers",
        "following_url": "https://api.github.com/users/azooinmyluggage/following{/other_user}",
        "gists_url": "https://api.github.com/users/azooinmyluggage/gists{/gist_id}",
        "starred_url": "https://api.github.com/users/azooinmyluggage/starred{/owner}{/repo}",
        "subscriptions_url": "https://api.github.com/users/azooinmyluggage/subscriptions",
        "organizations_url": "https://api.github.com/users/azooinmyluggage/orgs",
        "repos_url": "https://api.github.com/users/azooinmyluggage/repos",
        "events_url": "https://api.github.com/users/azooinmyluggage/events{/privacy}",
        "received_events_url": "https://api.github.com/users/azooinmyluggage/received_events",
        "type": "User",
        "site_admin": true
      },
      "event": "labeled",
      "commit_id": null,
      "commit_url": null,
      "created_at": "2020-09-18T07:57:57Z",
      "label": {
        "name": "Epic",
        "color": "654bcc"
      },
      "performed_via_github_app": null
    },
    {
      "id": 3781408029,
      "node_id": "MDE0Ok1lbnRpb25lZEV2ZW50Mzc4MTQwODAyOQ==",
      "url": "https://api.github.com/repos/github/GitHub-EcoSystem/issues/events/3781408029",
      "actor": {
        "login": "shailesh-sk",
        "id": 43347673,
        "node_id": "MDQ6VXNlcjQzMzQ3Njcz",
        "avatar_url": "https://avatars2.githubusercontent.com/u/43347673?v=4",
        "gravatar_id": "",
        "url": "https://api.github.com/users/shailesh-sk",
        "html_url": "https://github.com/shailesh-sk",
        "followers_url": "https://api.github.com/users/shailesh-sk/followers",
        "following_url": "https://api.github.com/users/shailesh-sk/following{/other_user}",
        "gists_url": "https://api.github.com/users/shailesh-sk/gists{/gist_id}",
        "starred_url": "https://api.github.com/users/shailesh-sk/starred{/owner}{/repo}",
        "subscriptions_url": "https://api.github.com/users/shailesh-sk/subscriptions",
        "organizations_url": "https://api.github.com/users/shailesh-sk/orgs",
        "repos_url": "https://api.github.com/users/shailesh-sk/repos",
        "events_url": "https://api.github.com/users/shailesh-sk/events{/privacy}",
        "received_events_url": "https://api.github.com/users/shailesh-sk/received_events",
        "type": "User",
        "site_admin": true
      },
      "event": "mentioned",
      "commit_id": null,
      "commit_url": null,
      "created_at": "2020-09-18T07:57:58Z",
      "performed_via_github_app": null
    },
    {
      "id": 3781408034,
      "node_id": "MDE1OlN1YnNjcmliZWRFdmVudDM3ODE0MDgwMzQ=",
      "url": "https://api.github.com/repos/github/GitHub-EcoSystem/issues/events/3781408034",
      "actor": {
        "login": "shailesh-sk",
        "id": 43347673,
        "node_id": "MDQ6VXNlcjQzMzQ3Njcz",
        "avatar_url": "https://avatars2.githubusercontent.com/u/43347673?v=4",
        "gravatar_id": "",
        "url": "https://api.github.com/users/shailesh-sk",
        "html_url": "https://github.com/shailesh-sk",
        "followers_url": "https://api.github.com/users/shailesh-sk/followers",
        "following_url": "https://api.github.com/users/shailesh-sk/following{/other_user}",
        "gists_url": "https://api.github.com/users/shailesh-sk/gists{/gist_id}",
        "starred_url": "https://api.github.com/users/shailesh-sk/starred{/owner}{/repo}",
        "subscriptions_url": "https://api.github.com/users/shailesh-sk/subscriptions",
        "organizations_url": "https://api.github.com/users/shailesh-sk/orgs",
        "repos_url": "https://api.github.com/users/shailesh-sk/repos",
        "events_url": "https://api.github.com/users/shailesh-sk/events{/privacy}",
        "received_events_url": "https://api.github.com/users/shailesh-sk/received_events",
        "type": "User",
        "site_admin": true
      },
      "event": "subscribed",
      "commit_id": null,
      "commit_url": null,
      "created_at": "2020-09-18T07:57:58Z",
      "performed_via_github_app": null
    },
    {
      "id": 3781408039,
      "node_id": "MDEzOkFzc2lnbmVkRXZlbnQzNzgxNDA4MDM5",
      "url": "https://api.github.com/repos/github/GitHub-EcoSystem/issues/events/3781408039",
      "actor": {
        "login": "ninallam",
        "id": 50437471,
        "node_id": "MDQ6VXNlcjUwNDM3NDcx",
        "avatar_url": "https://avatars1.githubusercontent.com/u/50437471?v=4",
        "gravatar_id": "",
        "url": "https://api.github.com/users/ninallam",
        "html_url": "https://github.com/ninallam",
        "followers_url": "https://api.github.com/users/ninallam/followers",
        "following_url": "https://api.github.com/users/ninallam/following{/other_user}",
        "gists_url": "https://api.github.com/users/ninallam/gists{/gist_id}",
        "starred_url": "https://api.github.com/users/ninallam/starred{/owner}{/repo}",
        "subscriptions_url": "https://api.github.com/users/ninallam/subscriptions",
        "organizations_url": "https://api.github.com/users/ninallam/orgs",
        "repos_url": "https://api.github.com/users/ninallam/repos",
        "events_url": "https://api.github.com/users/ninallam/events{/privacy}",
        "received_events_url": "https://api.github.com/users/ninallam/received_events",
        "type": "User",
        "site_admin": true
      },
      "event": "assigned",
      "commit_id": null,
      "commit_url": null,
      "created_at": "2020-09-18T07:57:58Z",
      "assignee": {
        "login": "ninallam",
        "id": 50437471,
        "node_id": "MDQ6VXNlcjUwNDM3NDcx",
        "avatar_url": "https://avatars1.githubusercontent.com/u/50437471?v=4",
        "gravatar_id": "",
        "url": "https://api.github.com/users/ninallam",
        "html_url": "https://github.com/ninallam",
        "followers_url": "https://api.github.com/users/ninallam/followers",
        "following_url": "https://api.github.com/users/ninallam/following{/other_user}",
        "gists_url": "https://api.github.com/users/ninallam/gists{/gist_id}",
        "starred_url": "https://api.github.com/users/ninallam/starred{/owner}{/repo}",
        "subscriptions_url": "https://api.github.com/users/ninallam/subscriptions",
        "organizations_url": "https://api.github.com/users/ninallam/orgs",
        "repos_url": "https://api.github.com/users/ninallam/repos",
        "events_url": "https://api.github.com/users/ninallam/events{/privacy}",
        "received_events_url": "https://api.github.com/users/ninallam/received_events",
        "type": "User",
        "site_admin": true
      },
      "assigner": {
        "login": "azooinmyluggage",
        "id": 6857119,
        "node_id": "MDQ6VXNlcjY4NTcxMTk=",
        "avatar_url": "https://avatars2.githubusercontent.com/u/6857119?v=4",
        "gravatar_id": "",
        "url": "https://api.github.com/users/azooinmyluggage",
        "html_url": "https://github.com/azooinmyluggage",
        "followers_url": "https://api.github.com/users/azooinmyluggage/followers",
        "following_url": "https://api.github.com/users/azooinmyluggage/following{/other_user}",
        "gists_url": "https://api.github.com/users/azooinmyluggage/gists{/gist_id}",
        "starred_url": "https://api.github.com/users/azooinmyluggage/starred{/owner}{/repo}",
        "subscriptions_url": "https://api.github.com/users/azooinmyluggage/subscriptions",
        "organizations_url": "https://api.github.com/users/azooinmyluggage/orgs",
        "repos_url": "https://api.github.com/users/azooinmyluggage/repos",
        "events_url": "https://api.github.com/users/azooinmyluggage/events{/privacy}",
        "received_events_url": "https://api.github.com/users/azooinmyluggage/received_events",
        "type": "User",
        "site_admin": true
      },
      "performed_via_github_app": null
    },
    {
      "id": 3781408042,
      "node_id": "MDE0Ok1lbnRpb25lZEV2ZW50Mzc4MTQwODA0Mg==",
      "url": "https://api.github.com/repos/github/GitHub-EcoSystem/issues/events/3781408042",
      "actor": {
        "login": "ninallam",
        "id": 50437471,
        "node_id": "MDQ6VXNlcjUwNDM3NDcx",
        "avatar_url": "https://avatars1.githubusercontent.com/u/50437471?v=4",
        "gravatar_id": "",
        "url": "https://api.github.com/users/ninallam",
        "html_url": "https://github.com/ninallam",
        "followers_url": "https://api.github.com/users/ninallam/followers",
        "following_url": "https://api.github.com/users/ninallam/following{/other_user}",
        "gists_url": "https://api.github.com/users/ninallam/gists{/gist_id}",
        "starred_url": "https://api.github.com/users/ninallam/starred{/owner}{/repo}",
        "subscriptions_url": "https://api.github.com/users/ninallam/subscriptions",
        "organizations_url": "https://api.github.com/users/ninallam/orgs",
        "repos_url": "https://api.github.com/users/ninallam/repos",
        "events_url": "https://api.github.com/users/ninallam/events{/privacy}",
        "received_events_url": "https://api.github.com/users/ninallam/received_events",
        "type": "User",
        "site_admin": true
      },
      "event": "mentioned",
      "commit_id": null,
      "commit_url": null,
      "created_at": "2020-09-18T07:57:58Z",
      "performed_via_github_app": null
    },
    {
      "id": 3781408046,
      "node_id": "MDE1OlN1YnNjcmliZWRFdmVudDM3ODE0MDgwNDY=",
      "url": "https://api.github.com/repos/github/GitHub-EcoSystem/issues/events/3781408046",
      "actor": {
        "login": "ninallam",
        "id": 50437471,
        "node_id": "MDQ6VXNlcjUwNDM3NDcx",
        "avatar_url": "https://avatars1.githubusercontent.com/u/50437471?v=4",
        "gravatar_id": "",
        "url": "https://api.github.com/users/ninallam",
        "html_url": "https://github.com/ninallam",
        "followers_url": "https://api.github.com/users/ninallam/followers",
        "following_url": "https://api.github.com/users/ninallam/following{/other_user}",
        "gists_url": "https://api.github.com/users/ninallam/gists{/gist_id}",
        "starred_url": "https://api.github.com/users/ninallam/starred{/owner}{/repo}",
        "subscriptions_url": "https://api.github.com/users/ninallam/subscriptions",
        "organizations_url": "https://api.github.com/users/ninallam/orgs",
        "repos_url": "https://api.github.com/users/ninallam/repos",
        "events_url": "https://api.github.com/users/ninallam/events{/privacy}",
        "received_events_url": "https://api.github.com/users/ninallam/received_events",
        "type": "User",
        "site_admin": true
      },
      "event": "subscribed",
      "commit_id": null,
      "commit_url": null,
      "created_at": "2020-09-18T07:57:58Z",
      "performed_via_github_app": null
    },
    {
      "id": 3781412555,
      "node_id": "MDE5OkFkZGVkVG9Qcm9qZWN0RXZlbnQzNzgxNDEyNTU1",
      "url": "https://api.github.com/repos/github/GitHub-EcoSystem/issues/events/3781412555",
      "actor": {
        "login": "azooinmyluggage",
        "id": 6857119,
        "node_id": "MDQ6VXNlcjY4NTcxMTk=",
        "avatar_url": "https://avatars2.githubusercontent.com/u/6857119?v=4",
        "gravatar_id": "",
        "url": "https://api.github.com/users/azooinmyluggage",
        "html_url": "https://github.com/azooinmyluggage",
        "followers_url": "https://api.github.com/users/azooinmyluggage/followers",
        "following_url": "https://api.github.com/users/azooinmyluggage/following{/other_user}",
        "gists_url": "https://api.github.com/users/azooinmyluggage/gists{/gist_id}",
        "starred_url": "https://api.github.com/users/azooinmyluggage/starred{/owner}{/repo}",
        "subscriptions_url": "https://api.github.com/users/azooinmyluggage/subscriptions",
        "organizations_url": "https://api.github.com/users/azooinmyluggage/orgs",
        "repos_url": "https://api.github.com/users/azooinmyluggage/repos",
        "events_url": "https://api.github.com/users/azooinmyluggage/events{/privacy}",
        "received_events_url": "https://api.github.com/users/azooinmyluggage/received_events",
        "type": "User",
        "site_admin": true
      },
      "event": "added_to_project",
      "commit_id": null,
      "commit_url": null,
      "created_at": "2020-09-18T07:59:13Z",
      "project_card": {
        "id": 45735487,
        "url": "https://api.github.com/projects/columns/cards/45735487",
        "project_id": 4118067,
        "project_url": "https://api.github.com/projects/4118067",
        "column_name": "In Progress"
      },
      "performed_via_github_app": null
    },
    {
      "id": 3781417931,
      "node_id": "MDEyOkxhYmVsZWRFdmVudDM3ODE0MTc5MzE=",
      "url": "https://api.github.com/repos/github/GitHub-EcoSystem/issues/events/3781417931",
      "actor": {
        "login": "azooinmyluggage",
        "id": 6857119,
        "node_id": "MDQ6VXNlcjY4NTcxMTk=",
        "avatar_url": "https://avatars2.githubusercontent.com/u/6857119?v=4",
        "gravatar_id": "",
        "url": "https://api.github.com/users/azooinmyluggage",
        "html_url": "https://github.com/azooinmyluggage",
        "followers_url": "https://api.github.com/users/azooinmyluggage/followers",
        "following_url": "https://api.github.com/users/azooinmyluggage/following{/other_user}",
        "gists_url": "https://api.github.com/users/azooinmyluggage/gists{/gist_id}",
        "starred_url": "https://api.github.com/users/azooinmyluggage/starred{/owner}{/repo}",
        "subscriptions_url": "https://api.github.com/users/azooinmyluggage/subscriptions",
        "organizations_url": "https://api.github.com/users/azooinmyluggage/orgs",
        "repos_url": "https://api.github.com/users/azooinmyluggage/repos",
        "events_url": "https://api.github.com/users/azooinmyluggage/events{/privacy}",
        "received_events_url": "https://api.github.com/users/azooinmyluggage/received_events",
        "type": "User",
        "site_admin": true
      },
      "event": "labeled",
      "commit_id": null,
      "commit_url": null,
      "created_at": "2020-09-18T08:00:37Z",
      "label": {
        "name": "Team: PowerApp",
        "color": "c9467a"
      },
      "performed_via_github_app": null
    },
    {
      "id": 3781418546,
      "node_id": "MDEyOkxhYmVsZWRFdmVudDM3ODE0MTg1NDY=",
      "url": "https://api.github.com/repos/github/GitHub-EcoSystem/issues/events/3781418546",
      "actor": {
        "login": "azooinmyluggage",
        "id": 6857119,
        "node_id": "MDQ6VXNlcjY4NTcxMTk=",
        "avatar_url": "https://avatars2.githubusercontent.com/u/6857119?v=4",
        "gravatar_id": "",
        "url": "https://api.github.com/users/azooinmyluggage",
        "html_url": "https://github.com/azooinmyluggage",
        "followers_url": "https://api.github.com/users/azooinmyluggage/followers",
        "following_url": "https://api.github.com/users/azooinmyluggage/following{/other_user}",
        "gists_url": "https://api.github.com/users/azooinmyluggage/gists{/gist_id}",
        "starred_url": "https://api.github.com/users/azooinmyluggage/starred{/owner}{/repo}",
        "subscriptions_url": "https://api.github.com/users/azooinmyluggage/subscriptions",
        "organizations_url": "https://api.github.com/users/azooinmyluggage/orgs",
        "repos_url": "https://api.github.com/users/azooinmyluggage/repos",
        "events_url": "https://api.github.com/users/azooinmyluggage/events{/privacy}",
        "received_events_url": "https://api.github.com/users/azooinmyluggage/received_events",
        "type": "User",
        "site_admin": true
      },
      "event": "labeled",
      "commit_id": null,
      "commit_url": null,
      "created_at": "2020-09-18T08:00:46Z",
      "label": {
        "name": "Milestone: Ignite",
        "color": "dae819"
      },
      "performed_via_github_app": null
    }
  ]
}