{
  "status": 200,
  "url": "https://api.github.com/repos/github/azure-integration/issues/40/events?per_page=100",
  "headers": {
    "access-control-allow-origin": "*",
    "access-control-expose-headers": "ETag, Link, Location, Retry-After, X-GitHub-OTP, X-RateLimit-Limit, X-RateLimit-Remaining, X-RateLimit-Used, X-RateLimit-Reset, X-OAuth-Scopes, X-Accepted-OAuth-Scopes, X-Poll-Interval, X-GitHub-Media-Type, Deprecation, Sunset",
    "cache-control": "private, max-age=60, s-maxage=60",
    "connection": "close",
    "content-encoding": "gzip",
    "content-security-policy": "default-src 'none'",
    "content-type": "application/json; charset=utf-8",
    "date": "Wed, 30 Sep 2020 10:59:35 GMT",
    "etag": "W/\"2324cea87eaf69824fdb3e62c8f9038c94711609a746ba24a160ee41fb839a3a\"",
    "referrer-policy": "origin-when-cross-origin, strict-origin-when-cross-origin",
    "server": "GitHub.com",
    "status": "200 OK",
    "strict-transport-security": "max-age=31536000; includeSubdomains; preload",
    "transfer-encoding": "chunked",
    "vary": "Accept, Authorization, Cookie, X-GitHub-OTP, Accept-Encoding, Accept, X-Requested-With, Accept-Encoding",
    "x-accepted-oauth-scopes": "repo",
    "x-content-type-options": "nosniff",
    "x-frame-options": "deny",
    "x-github-media-type": "github.squirrel-girl-preview; format=json, github.inertia-preview; format=json, github.starfox-preview; format=json, github.mockingbird-preview; param=sailor-v-preview; format=json, github.squirrel-girl-preview; format=json, github.inertia-preview; format=json, github.starfox-preview; format=json, github.mockingbird-preview; param=sailor-v-preview; format=json",
    "x-github-request-id": "07B7:A4DF:60B2DDD:7375BB9:5F746516",
    "x-oauth-scopes": "admin:enterprise, admin:gpg_key, admin:org, admin:org_hook, admin:public_key, admin:repo_hook, gist, repo, user, workflow, write:discussion, write:packages",
    "x-ratelimit-limit": "5000",
    "x-ratelimit-remaining": "3679",
    "x-ratelimit-reset": "1601465977",
    "x-ratelimit-used": "1321",
    "x-xss-protection": "1; mode=block"
  },
  "data": [
    {
      "id": 3781578733,
      "node_id": "MDI1OkNvbnZlcnRlZE5vdGVUb0lzc3VlRXZlbnQzNzgxNTc4NzMz",
      "url": "https://api.github.com/repos/github/azure-integration/issues/events/3781578733",
      "actor": {
        "login": "bishal-pdMSFT",
        "id": 7830141,
        "node_id": "MDQ6VXNlcjc4MzAxNDE=",
        "avatar_url": "https://avatars3.githubusercontent.com/u/7830141?v=4",
        "gravatar_id": "",
        "url": "https://api.github.com/users/bishal-pdMSFT",
        "html_url": "https://github.com/bishal-pdMSFT",
        "followers_url": "https://api.github.com/users/bishal-pdMSFT/followers",
        "following_url": "https://api.github.com/users/bishal-pdMSFT/following{/other_user}",
        "gists_url": "https://api.github.com/users/bishal-pdMSFT/gists{/gist_id}",
        "starred_url": "https://api.github.com/users/bishal-pdMSFT/starred{/owner}{/repo}",
        "subscriptions_url": "https://api.github.com/users/bishal-pdMSFT/subscriptions",
        "organizations_url": "https://api.github.com/users/bishal-pdMSFT/orgs",
        "repos_url": "https://api.github.com/users/bishal-pdMSFT/repos",
        "events_url": "https://api.github.com/users/bishal-pdMSFT/events{/privacy}",
        "received_events_url": "https://api.github.com/users/bishal-pdMSFT/received_events",
        "type": "User",
        "site_admin": true
      },
      "event": "converted_note_to_issue",
      "commit_id": null,
      "commit_url": null,
      "created_at": "2020-09-18T08:43:39Z",
      "project_card": {
        "id": 45738577,
        "url": "https://api.github.com/projects/columns/cards/45738577",
        "project_id": 5431263,
        "project_url": "https://api.github.com/projects/5431263",
        "column_name": "Committed"
      },
      "performed_via_github_app": null
    },
    {
      "id": 3781579264,
      "node_id": "MDEzOkFzc2lnbmVkRXZlbnQzNzgxNTc5MjY0",
      "url": "https://api.github.com/repos/github/azure-integration/issues/events/3781579264",
      "actor": {
        "login": "vineetmimrot",
        "id": 4174297,
        "node_id": "MDQ6VXNlcjQxNzQyOTc=",
        "avatar_url": "https://avatars1.githubusercontent.com/u/4174297?v=4",
        "gravatar_id": "",
        "url": "https://api.github.com/users/vineetmimrot",
        "html_url": "https://github.com/vineetmimrot",
        "followers_url": "https://api.github.com/users/vineetmimrot/followers",
        "following_url": "https://api.github.com/users/vineetmimrot/following{/other_user}",
        "gists_url": "https://api.github.com/users/vineetmimrot/gists{/gist_id}",
        "starred_url": "https://api.github.com/users/vineetmimrot/starred{/owner}{/repo}",
        "subscriptions_url": "https://api.github.com/users/vineetmimrot/subscriptions",
        "organizations_url": "https://api.github.com/users/vineetmimrot/orgs",
        "repos_url": "https://api.github.com/users/vineetmimrot/repos",
        "events_url": "https://api.github.com/users/vineetmimrot/events{/privacy}",
        "received_events_url": "https://api.github.com/users/vineetmimrot/received_events",
        "type": "User",
        "site_admin": true
      },
      "event": "assigned",
      "commit_id": null,
      "commit_url": null,
      "created_at": "2020-09-18T08:43:48Z",
      "assignee": {
        "login": "vineetmimrot",
        "id": 4174297,
        "node_id": "MDQ6VXNlcjQxNzQyOTc=",
        "avatar_url": "https://avatars1.githubusercontent.com/u/4174297?v=4",
        "gravatar_id": "",
        "url": "https://api.github.com/users/vineetmimrot",
        "html_url": "https://github.com/vineetmimrot",
        "followers_url": "https://api.github.com/users/vineetmimrot/followers",
        "following_url": "https://api.github.com/users/vineetmimrot/following{/other_user}",
        "gists_url": "https://api.github.com/users/vineetmimrot/gists{/gist_id}",
        "starred_url": "https://api.github.com/users/vineetmimrot/starred{/owner}{/repo}",
        "subscriptions_url": "https://api.github.com/users/vineetmimrot/subscriptions",
        "organizations_url": "https://api.github.com/users/vineetmimrot/orgs",
        "repos_url": "https://api.github.com/users/vineetmimrot/repos",
        "events_url": "https://api.github.com/users/vineetmimrot/events{/privacy}",
        "received_events_url": "https://api.github.com/users/vineetmimrot/received_events",
        "type": "User",
        "site_admin": true
      },
      "assigner": {
        "login": "bishal-pdMSFT",
        "id": 7830141,
        "node_id": "MDQ6VXNlcjc4MzAxNDE=",
        "avatar_url": "https://avatars3.githubusercontent.com/u/7830141?v=4",
        "gravatar_id": "",
        "url": "https://api.github.com/users/bishal-pdMSFT",
        "html_url": "https://github.com/bishal-pdMSFT",
        "followers_url": "https://api.github.com/users/bishal-pdMSFT/followers",
        "following_url": "https://api.github.com/users/bishal-pdMSFT/following{/other_user}",
        "gists_url": "https://api.github.com/users/bishal-pdMSFT/gists{/gist_id}",
        "starred_url": "https://api.github.com/users/bishal-pdMSFT/starred{/owner}{/repo}",
        "subscriptions_url": "https://api.github.com/users/bishal-pdMSFT/subscriptions",
        "organizations_url": "https://api.github.com/users/bishal-pdMSFT/orgs",
        "repos_url": "https://api.github.com/users/bishal-pdMSFT/repos",
        "events_url": "https://api.github.com/users/bishal-pdMSFT/events{/privacy}",
        "received_events_url": "https://api.github.com/users/bishal-pdMSFT/received_events",
        "type": "User",
        "site_admin": true
      },
      "performed_via_github_app": null
    },
    {
      "id": 3781579641,
      "node_id": "MDEyOkxhYmVsZWRFdmVudDM3ODE1Nzk2NDE=",
      "url": "https://api.github.com/repos/github/azure-integration/issues/events/3781579641",
      "actor": {
        "login": "bishal-pdMSFT",
        "id": 7830141,
        "node_id": "MDQ6VXNlcjc4MzAxNDE=",
        "avatar_url": "https://avatars3.githubusercontent.com/u/7830141?v=4",
        "gravatar_id": "",
        "url": "https://api.github.com/users/bishal-pdMSFT",
        "html_url": "https://github.com/bishal-pdMSFT",
        "followers_url": "https://api.github.com/users/bishal-pdMSFT/followers",
        "following_url": "https://api.github.com/users/bishal-pdMSFT/following{/other_user}",
        "gists_url": "https://api.github.com/users/bishal-pdMSFT/gists{/gist_id}",
        "starred_url": "https://api.github.com/users/bishal-pdMSFT/starred{/owner}{/repo}",
        "subscriptions_url": "https://api.github.com/users/bishal-pdMSFT/subscriptions",
        "organizations_url": "https://api.github.com/users/bishal-pdMSFT/orgs",
        "repos_url": "https://api.github.com/users/bishal-pdMSFT/repos",
        "events_url": "https://api.github.com/users/bishal-pdMSFT/events{/privacy}",
        "received_events_url": "https://api.github.com/users/bishal-pdMSFT/received_events",
        "type": "User",
        "site_admin": true
      },
      "event": "labeled",
      "commit_id": null,
      "commit_url": null,
      "created_at": "2020-09-18T08:43:54Z",
      "label": {
        "name": "Feature",
        "color": "93e072"
      },
      "performed_via_github_app": null
    },
    {
      "id": 3781579953,
      "node_id": "MDE1Ok1pbGVzdG9uZWRFdmVudDM3ODE1Nzk5NTM=",
      "url": "https://api.github.com/repos/github/azure-integration/issues/events/3781579953",
      "actor": {
        "login": "bishal-pdMSFT",
        "id": 7830141,
        "node_id": "MDQ6VXNlcjc4MzAxNDE=",
        "avatar_url": "https://avatars3.githubusercontent.com/u/7830141?v=4",
        "gravatar_id": "",
        "url": "https://api.github.com/users/bishal-pdMSFT",
        "html_url": "https://github.com/bishal-pdMSFT",
        "followers_url": "https://api.github.com/users/bishal-pdMSFT/followers",
        "following_url": "https://api.github.com/users/bishal-pdMSFT/following{/other_user}",
        "gists_url": "https://api.github.com/users/bishal-pdMSFT/gists{/gist_id}",
        "starred_url": "https://api.github.com/users/bishal-pdMSFT/starred{/owner}{/repo}",
        "subscriptions_url": "https://api.github.com/users/bishal-pdMSFT/subscriptions",
        "organizations_url": "https://api.github.com/users/bishal-pdMSFT/orgs",
        "repos_url": "https://api.github.com/users/bishal-pdMSFT/repos",
        "events_url": "https://api.github.com/users/bishal-pdMSFT/events{/privacy}",
        "received_events_url": "https://api.github.com/users/bishal-pdMSFT/received_events",
        "type": "User",
        "site_admin": true
      },
      "event": "milestoned",
      "commit_id": null,
      "commit_url": null,
      "created_at": "2020-09-18T08:43:59Z",
      "milestone": {
        "title": "176.3"
      },
      "performed_via_github_app": null
    },
    {
      "id": 3796338363,
      "node_id": "MDI2Ok1vdmVkQ29sdW1uc0luUHJvamVjdEV2ZW50Mzc5NjMzODM2Mw==",
      "url": "https://api.github.com/repos/github/azure-integration/issues/events/3796338363",
      "actor": {
        "login": "NinadKavimandan",
        "id": 23234879,
        "node_id": "MDQ6VXNlcjIzMjM0ODc5",
        "avatar_url": "https://avatars2.githubusercontent.com/u/23234879?v=4",
        "gravatar_id": "",
        "url": "https://api.github.com/users/NinadKavimandan",
        "html_url": "https://github.com/NinadKavimandan",
        "followers_url": "https://api.github.com/users/NinadKavimandan/followers",
        "following_url": "https://api.github.com/users/NinadKavimandan/following{/other_user}",
        "gists_url": "https://api.github.com/users/NinadKavimandan/gists{/gist_id}",
        "starred_url": "https://api.github.com/users/NinadKavimandan/starred{/owner}{/repo}",
        "subscriptions_url": "https://api.github.com/users/NinadKavimandan/subscriptions",
        "organizations_url": "https://api.github.com/users/NinadKavimandan/orgs",
        "repos_url": "https://api.github.com/users/NinadKavimandan/repos",
        "events_url": "https://api.github.com/users/NinadKavimandan/events{/privacy}",
        "received_events_url": "https://api.github.com/users/NinadKavimandan/received_events",
        "type": "User",
        "site_admin": true
      },
      "event": "moved_columns_in_project",
      "commit_id": null,
      "commit_url": null,
      "created_at": "2020-09-23T05:45:25Z",
      "project_card": {
        "id": 45738577,
        "url": "https://api.github.com/projects/columns/cards/45738577",
        "project_id": 5431263,
        "project_url": "https://api.github.com/projects/5431263",
        "column_name": "In review",
        "previous_column_name": "Committed"
      },
      "performed_via_github_app": null
    },
    {
      "id": 3804150811,
      "node_id": "MDExOkNsb3NlZEV2ZW50MzgwNDE1MDgxMQ==",
      "url": "https://api.github.com/repos/github/azure-integration/issues/events/3804150811",
      "actor": {
        "login": "vineetmimrot",
        "id": 4174297,
        "node_id": "MDQ6VXNlcjQxNzQyOTc=",
        "avatar_url": "https://avatars1.githubusercontent.com/u/4174297?v=4",
        "gravatar_id": "",
        "url": "https://api.github.com/users/vineetmimrot",
        "html_url": "https://github.com/vineetmimrot",
        "followers_url": "https://api.github.com/users/vineetmimrot/followers",
        "following_url": "https://api.github.com/users/vineetmimrot/following{/other_user}",
        "gists_url": "https://api.github.com/users/vineetmimrot/gists{/gist_id}",
        "starred_url": "https://api.github.com/users/vineetmimrot/starred{/owner}{/repo}",
        "subscriptions_url": "https://api.github.com/users/vineetmimrot/subscriptions",
        "organizations_url": "https://api.github.com/users/vineetmimrot/orgs",
        "repos_url": "https://api.github.com/users/vineetmimrot/repos",
        "events_url": "https://api.github.com/users/vineetmimrot/events{/privacy}",
        "received_events_url": "https://api.github.com/users/vineetmimrot/received_events",
        "type": "User",
        "site_admin": true
      },
      "event": "closed",
      "commit_id": null,
      "commit_url": null,
      "created_at": "2020-09-24T16:43:13Z",
      "performed_via_github_app": null
    },
    {
      "id": 3806112894,
      "node_id": "MDI2Ok1vdmVkQ29sdW1uc0luUHJvamVjdEV2ZW50MzgwNjExMjg5NA==",
      "url": "https://api.github.com/repos/github/azure-integration/issues/events/3806112894",
      "actor": {
        "login": "vineetmimrot",
        "id": 4174297,
        "node_id": "MDQ6VXNlcjQxNzQyOTc=",
        "avatar_url": "https://avatars1.githubusercontent.com/u/4174297?v=4",
        "gravatar_id": "",
        "url": "https://api.github.com/users/vineetmimrot",
        "html_url": "https://github.com/vineetmimrot",
        "followers_url": "https://api.github.com/users/vineetmimrot/followers",
        "following_url": "https://api.github.com/users/vineetmimrot/following{/other_user}",
        "gists_url": "https://api.github.com/users/vineetmimrot/gists{/gist_id}",
        "starred_url": "https://api.github.com/users/vineetmimrot/starred{/owner}{/repo}",
        "subscriptions_url": "https://api.github.com/users/vineetmimrot/subscriptions",
        "organizations_url": "https://api.github.com/users/vineetmimrot/orgs",
        "repos_url": "https://api.github.com/users/vineetmimrot/repos",
        "events_url": "https://api.github.com/users/vineetmimrot/events{/privacy}",
        "received_events_url": "https://api.github.com/users/vineetmimrot/received_events",
        "type": "User",
        "site_admin": true
      },
      "event": "moved_columns_in_project",
      "commit_id": null,
      "commit_url": null,
      "created_at": "2020-09-25T05:50:45Z",
      "project_card": {
        "id": 45738577,
        "url": "https://api.github.com/projects/columns/cards/45738577",
        "project_id": 5431263,
        "project_url": "https://api.github.com/projects/5431263",
        "column_name": "Done",
        "previous_column_name": "In review"
      },
      "performed_via_github_app": null
    }
  ]
}